{"cameraMode":{"drawMode":0,"name":"Shaded","section":"Shading Mode"},"sceneLighting":true,"audioPlay":false,"sceneViewState":{"m_AlwaysRefresh":false,"showFog":true,"showSkybox":true,"showFlares":true,"showImageEffects":true,"showParticleSystems":true,"showVisualEffectGraphs":true,"m_FxEnabled":true},"in2DMode":false,"pivot":{"x":4.332942008972168,"y":0.8656587600708008,"z":-11.607756614685059},"rotation":{"x":-0.28820842504501345,"y":0.5130571126937866,"z":-0.1880422830581665,"w":-0.7863520979881287},"size":5.153746604919434,"orthographic":false}